{
  "Header": "F9538B831F363243BAAE0D17865D08547DA2DB215D000000",
  "Records": [
    {
      "RootId": 1,
      "HeaderId": -1,
      "MajorVersion": 1,
      "MinorVersion": 0,
      "RecordTypeEnum": "SerializedStreamHeader"
    },
    {
      "LibraryId": 2,
      "LibraryName": "X",
      "RecordTypeEnum": "BinaryLibrary"
    },
    {
      "ClassInfo": {
        "ObjectId": 1,
        "Name": "DM",
        "MemberCount": 31,
        "MemberNames": [
          "DM:DN",
          "DM:DD",
          "DM:SE",
          "DM:LL:Count",
          "DM:LL:0",
          "DM:LL:1",
          "DM:LL:2",
          "DM:LL:3",
          "DM:LL:4",
          "DM:LL:5",
          "DM:LL:6",
          "DM:LL:7",
          "DM:LL:8",
          "DM:LL:9",
          "DM:LL:10",
          "DM:LL:11",
          "DM:LL:12",
          "DM:LL:13",
          "DM:LL:14",
          "DM:LL:15",
          "DM:LL:16",
          "DM:LL:17",
          "DM:LL:18",
          "DM:LL:19",
          "DM:LL:20",
          "DM:LL:21",
          "DM:A:Count",
          "DM:A:0",
          "DM:A:1",
          "DM:IC",
          "DM:P"
        ]
      },
      "MemberTypeInfo": {
        "BinaryTypeEnums": [
          "String",
          "String",
          "Class",
          "Primitive",
          "String",
          "String",
          "String",
          "String",
          "String",
          "String",
          "String",
          "String",
          "String",
          "String",
          "String",
          "String",
          "String",
          "String",
          "String",
          "String",
          "String",
          "String",
          "String",
          "String",
          "String",
          "String",
          "Primitive",
          "Class",
          "Class",
          "Primitive",
          "Primitive"
        ],
        "AdditionalInfos": [
          null,
          null,
          {
            "TypeName": "J",
            "LibraryId": 2
          },
          "Int32",
          null,
          null,
          null,
          null,
          null,
          null,
          null,
          null,
          null,
          null,
          null,
          null,
          null,
          null,
          null,
          null,
          null,
          null,
          null,
          null,
          null,
          null,
          "Int32",
          {
            "TypeName": "A4",
            "LibraryId": 2
          },
          {
            "TypeName": "A4",
            "LibraryId": 2
          },
          "Boolean",
          "Boolean"
        ]
      },
      "LibraryId": 2,
      "Values": [
        {
          "ObjectId": 3,
          "Value": "xpbl_ojyc_Consoles",
          "RecordTypeEnum": "BinaryObjectString"
        },
        {
          "ObjectId": 4,
          "Value": "",
          "RecordTypeEnum": "BinaryObjectString"
        },
        {
          "IdRef": 5,
          "RecordTypeEnum": "MemberReference"
        },
        22,
        {
          "ObjectId": 6,
          "Value": "English",
          "RecordTypeEnum": "BinaryObjectString"
        },
        {
          "ObjectId": 7,
          "Value": "English",
          "RecordTypeEnum": "BinaryObjectString"
        },
        {
          "ObjectId": 8,
          "Value": "English",
          "RecordTypeEnum": "BinaryObjectString"
        },
        {
          "ObjectId": 9,
          "Value": "English",
          "RecordTypeEnum": "BinaryObjectString"
        },
        {
          "ObjectId": 10,
          "Value": "English",
          "RecordTypeEnum": "BinaryObjectString"
        },
        {
          "ObjectId": 11,
          "Value": "English",
          "RecordTypeEnum": "BinaryObjectString"
        },
        {
          "ObjectId": 12,
          "Value": "English",
          "RecordTypeEnum": "BinaryObjectString"
        },
        {
          "ObjectId": 13,
          "Value": "English",
          "RecordTypeEnum": "BinaryObjectString"
        },
        {
          "ObjectId": 14,
          "Value": "English",
          "RecordTypeEnum": "BinaryObjectString"
        },
        {
          "ObjectId": 15,
          "Value": "English",
          "RecordTypeEnum": "BinaryObjectString"
        },
        {
          "ObjectId": 16,
          "Value": "English",
          "RecordTypeEnum": "BinaryObjectString"
        },
        {
          "ObjectId": 17,
          "Value": "English",
          "RecordTypeEnum": "BinaryObjectString"
        },
        {
          "ObjectId": 18,
          "Value": "English",
          "RecordTypeEnum": "BinaryObjectString"
        },
        {
          "ObjectId": 19,
          "Value": "English",
          "RecordTypeEnum": "BinaryObjectString"
        },
        {
          "ObjectId": 20,
          "Value": "English",
          "RecordTypeEnum": "BinaryObjectString"
        },
        {
          "ObjectId": 21,
          "Value": "English",
          "RecordTypeEnum": "BinaryObjectString"
        },
        {
          "ObjectId": 22,
          "Value": "English",
          "RecordTypeEnum": "BinaryObjectString"
        },
        {
          "ObjectId": 23,
          "Value": "English",
          "RecordTypeEnum": "BinaryObjectString"
        },
        {
          "ObjectId": 24,
          "Value": "English",
          "RecordTypeEnum": "BinaryObjectString"
        },
        {
          "ObjectId": 25,
          "Value": "English",
          "RecordTypeEnum": "BinaryObjectString"
        },
        {
          "ObjectId": 26,
          "Value": "English",
          "RecordTypeEnum": "BinaryObjectString"
        },
        {
          "ObjectId": 27,
          "Value": "English",
          "RecordTypeEnum": "BinaryObjectString"
        },
        2,
        {
          "IdRef": 28,
          "RecordTypeEnum": "MemberReference"
        },
        {
          "IdRef": 29,
          "RecordTypeEnum": "MemberReference"
        },
        true,
        false
      ],
      "RecordTypeEnum": "ClassWithMembersAndTypes"
    },
    {
      "ClassInfo": {
        "ObjectId": 5,
        "Name": "J",
        "MemberCount": 4,
        "MemberNames": [
          "CE:CC",
          "CE:PNS:Count",
          "CE:PNS:0",
          "CE:N"
        ]
      },
      "MemberTypeInfo": {
        "BinaryTypeEnums": [
          "Object",
          "Primitive",
          "Class",
          "String"
        ],
        "AdditionalInfos": [
          null,
          "Int32",
          {
            "TypeName": "Q",
            "LibraryId": 2
          },
          null
        ]
      },
      "LibraryId": 2,
      "Values": [
        {
          "RecordTypeEnum": "ObjectNull"
        },
        1,
        {
          "IdRef": 30,
          "RecordTypeEnum": "MemberReference"
        },
        {
          "ObjectId": 31,
          "Value": "Start Element",
          "RecordTypeEnum": "BinaryObjectString"
        }
      ],
      "RecordTypeEnum": "ClassWithMembersAndTypes"
    },
    {
      "ClassInfo": {
        "ObjectId": 28,
        "Name": "A4",
        "MemberCount": 2,
        "MemberNames": [
          "A4:N",
          "A4:P"
        ]
      },
      "MemberTypeInfo": {
        "BinaryTypeEnums": [
          "String",
          "Object"
        ],
        "AdditionalInfos": [
          null,
          null
        ]
      },
      "LibraryId": 2,
      "Values": [
        {
          "ObjectId": 32,
          "Value": "interface",
          "RecordTypeEnum": "BinaryObjectString"
        },
        {
          "RecordTypeEnum": "ObjectNull"
        }
      ],
      "RecordTypeEnum": "ClassWithMembersAndTypes"
    },
    {
      "ObjectId": 29,
      "MetadataId": 28,
      "Values": [
        {
          "ObjectId": 33,
          "Value": "player",
          "RecordTypeEnum": "BinaryObjectString"
        },
        {
          "RecordTypeEnum": "ObjectNull"
        }
      ],
      "RecordTypeEnum": "ClassWithId"
    },
    {
      "ClassInfo": {
        "ObjectId": 30,
        "Name": "Q",
        "MemberCount": 12,
        "MemberNames": [
          "CE:CC",
          "CE:PNS:Count",
          "CE:PNS:0",
          "CE:PNS:1",
          "CE:N",
          "SE:RA:Count",
          "SE:LT:Count",
          "SE:LT:0:Key",
          "SE:LT:0:Value",
          "Q:PA:Count",
          "Q:Q",
          "Q:A"
        ]
      },
      "MemberTypeInfo": {
        "BinaryTypeEnums": [
          "Object",
          "Primitive",
          "Class",
          "Class",
          "String",
          "Primitive",
          "Primitive",
          "String",
          "String",
          "Primitive",
          "Class",
          "Class"
        ],
        "AdditionalInfos": [
          null,
          "Int32",
          {
            "TypeName": "Q",
            "LibraryId": 2
          },
          {
            "TypeName": "Q",
            "LibraryId": 2
          },
          null,
          "Int32",
          "Int32",
          null,
          null,
          "Int32",
          {
            "TypeName": "A4",
            "LibraryId": 2
          },
          {
            "TypeName": "A4",
            "LibraryId": 2
          }
        ]
      },
      "LibraryId": 2,
      "Values": [
        {
          "RecordTypeEnum": "ObjectNull"
        },
        2,
        {
          "IdRef": 34,
          "RecordTypeEnum": "MemberReference"
        },
        {
          "IdRef": 35,
          "RecordTypeEnum": "MemberReference"
        },
        {
          "ObjectId": 36,
          "Value": " (9deaf370-2aea-420f-915f-e445dcb91adb)*",
          "RecordTypeEnum": "BinaryObjectString"
        },
        0,
        1,
        {
          "IdRef": 27,
          "RecordTypeEnum": "MemberReference"
        },
        {
          "IdRef": 4,
          "RecordTypeEnum": "MemberReference"
        },
        0,
        {
          "IdRef": 28,
          "RecordTypeEnum": "MemberReference"
        },
        {
          "IdRef": 29,
          "RecordTypeEnum": "MemberReference"
        }
      ],
      "RecordTypeEnum": "ClassWithMembersAndTypes"
    },
    {
      "ClassInfo": {
        "ObjectId": 34,
        "Name": "Q",
        "MemberCount": 12,
        "MemberNames": [
          "CE:CC",
          "CE:PNS:Count",
          "CE:N",
          "SE:RA:Count",
          "SE:LT:Count",
          "SE:LT:0:Key",
          "SE:LT:0:Value",
          "Q:PA:Count",
          "Q:PA:0",
          "Q:PA:1",
          "Q:Q",
          "Q:A"
        ]
      },
      "MemberTypeInfo": {
        "BinaryTypeEnums": [
          "Class",
          "Primitive",
          "String",
          "Primitive",
          "Primitive",
          "String",
          "String",
          "Primitive",
          "Class",
          "Class",
          "Class",
          "Class"
        ],
        "AdditionalInfos": [
          {
            "TypeName": "CAC",
            "LibraryId": 2
          },
          "Int32",
          null,
          "Int32",
          "Int32",
          null,
          null,
          "Int32",
          {
            "TypeName": "A3",
            "LibraryId": 2
          },
          {
            "TypeName": "A3",
            "LibraryId": 2
          },
          {
            "TypeName": "A4",
            "LibraryId": 2
          },
          {
            "TypeName": "A4",
            "LibraryId": 2
          }
        ]
      },
      "LibraryId": 2,
      "Values": [
        {
          "IdRef": 41,
          "RecordTypeEnum": "MemberReference"
        },
        0,
        {
          "ObjectId": 42,
          "Value": "::The screen is blank.:: (42243030-143b-419b-8c70-567fce438be9)",
          "RecordTypeEnum": "BinaryObjectString"
        },
        0,
        1,
        {
          "IdRef": 7,
          "RecordTypeEnum": "MemberReference"
        },
        {
          "ObjectId": 44,
          "Value": "::The screen is blank.::",
          "RecordTypeEnum": "BinaryObjectString"
        },
        2,
        {
          "IdRef": 45,
          "RecordTypeEnum": "MemberReference"
        },
        {
          "IdRef": 46,
          "RecordTypeEnum": "MemberReference"
        },
        {
          "IdRef": 28,
          "RecordTypeEnum": "MemberReference"
        },
        {
          "IdRef": 29,
          "RecordTypeEnum": "MemberReference"
        }
      ],
      "RecordTypeEnum": "ClassWithMembersAndTypes"
    },
    {
      "ClassInfo": {
        "ObjectId": 35,
        "Name": "Q",
        "MemberCount": 11,
        "MemberNames": [
          "CE:CC",
          "CE:PNS:Count",
          "CE:PNS:0",
          "CE:N",
          "SE:RA:Count",
          "SE:LT:Count",
          "SE:LT:0:Key",
          "SE:LT:0:Value",
          "Q:PA:Count",
          "Q:Q",
          "Q:A"
        ]
      },
      "MemberTypeInfo": {
        "BinaryTypeEnums": [
          "Class",
          "Primitive",
          "Class",
          "String",
          "Primitive",
          "Primitive",
          "String",
          "String",
          "Primitive",
          "Class",
          "Class"
        ],
        "AdditionalInfos": [
          {
            "TypeName": "COC",
            "LibraryId": 2
          },
          "Int32",
          {
            "TypeName": "Q",
            "LibraryId": 2
          },
          null,
          "Int32",
          "Int32",
          null,
          null,
          "Int32",
          {
            "TypeName": "A4",
            "LibraryId": 2
          },
          {
            "TypeName": "A4",
            "LibraryId": 2
          }
        ]
      },
      "LibraryId": 2,
      "Values": [
        {
          "IdRef": 49,
          "RecordTypeEnum": "MemberReference"
        },
        1,
        {
          "IdRef": 50,
          "RecordTypeEnum": "MemberReference"
        },
        {
          "ObjectId": 51,
          "Value": "::Cruise control.Maneuvering thrusters o (9be7a5e2-2f2f-4817-958a-147c50eb3aee)*",
          "RecordTypeEnum": "BinaryObjectString"
        },
        0,
        1,
        {
          "IdRef": 27,
          "RecordTypeEnum": "MemberReference"
        },
        {
          "ObjectId": 53,
          "Value": "::Cruise control.\r\n\r\nManeuvering thrusters offline.::",
          "RecordTypeEnum": "BinaryObjectString"
        },
        0,
        {
          "IdRef": 28,
          "RecordTypeEnum": "MemberReference"
        },
        {
          "IdRef": 29,
          "RecordTypeEnum": "MemberReference"
        }
      ],
      "RecordTypeEnum": "ClassWithMembersAndTypes"
    },
    {
      "ClassInfo": {
        "ObjectId": 41,
        "Name": "CAC",
        "MemberCount": 4,
        "MemberNames": [
          "C:N",
          "CC:EC:Count",
          "CC:EC:0",
          "CC:EC:1"
        ]
      },
      "MemberTypeInfo": {
        "BinaryTypeEnums": [
          "Object",
          "Primitive",
          "Class",
          "Class"
        ],
        "AdditionalInfos": [
          null,
          "Int32",
          {
            "TypeName": "BC",
            "LibraryId": 2
          },
          {
            "TypeName": "BC",
            "LibraryId": 2
          }
        ]
      },
      "LibraryId": 2,
      "Values": [
        {
          "RecordTypeEnum": "ObjectNull"
        },
        2,
        {
          "IdRef": 56,
          "RecordTypeEnum": "MemberReference"
        },
        {
          "IdRef": 57,
          "RecordTypeEnum": "MemberReference"
        }
      ],
      "RecordTypeEnum": "ClassWithMembersAndTypes"
    },
    {
      "ClassInfo": {
        "ObjectId": 45,
        "Name": "A3",
        "MemberCount": 12,
        "MemberNames": [
          "CE:CC",
          "CE:PNS:Count",
          "CE:PNS:0",
          "CE:PNS:1",
          "CE:N",
          "SE:RA:Count",
          "SE:LT:Count",
          "SE:LT:0:Key",
          "SE:LT:0:Value",
          "A3:ID",
          "A3:D",
          "A3:DC"
        ]
      },
      "MemberTypeInfo": {
        "BinaryTypeEnums": [
          "Object",
          "Primitive",
          "Class",
          "Class",
          "String",
          "Primitive",
          "Primitive",
          "String",
          "String",
          "Primitive",
          "Primitive",
          "Object"
        ],
        "AdditionalInfos": [
          null,
          "Int32",
          {
            "TypeName": "Q",
            "LibraryId": 2
          },
          {
            "TypeName": "Q",
            "LibraryId": 2
          },
          null,
          "Int32",
          "Int32",
          null,
          null,
          "Boolean",
          "Boolean",
          null
        ]
      },
      "LibraryId": 2,
      "Values": [
        {
          "RecordTypeEnum": "ObjectNull"
        },
        2,
        {
          "IdRef": 58,
          "RecordTypeEnum": "MemberReference"
        },
        {
          "IdRef": 59,
          "RecordTypeEnum": "MemberReference"
        },
        {
          "ObjectId": 60,
          "Value": "::[Electronics] Repair the console.:: (f073e65e-cf3d-410a-a460-ec0592e2c4f3)",
          "RecordTypeEnum": "BinaryObjectString"
        },
        0,
        1,
        {
          "IdRef": 7,
          "RecordTypeEnum": "MemberReference"
        },
        {
          "ObjectId": 62,
          "Value": "::[Electronics] Repair the console.::",
          "RecordTypeEnum": "BinaryObjectString"
        },
        false,
        false,
        {
          "RecordTypeEnum": "ObjectNull"
        }
      ],
      "RecordTypeEnum": "ClassWithMembersAndTypes"
    },
    {
      "ClassInfo": {
        "ObjectId": 46,
        "Name": "A3",
        "MemberCount": 10,
        "MemberNames": [
          "CE:CC",
          "CE:PNS:Count",
          "CE:N",
          "SE:RA:Count",
          "SE:LT:Count",
          "SE:LT:0:Key",
          "SE:LT:0:Value",
          "A3:ID",
          "A3:D",
          "A3:DC"
        ]
      },
      "MemberTypeInfo": {
        "BinaryTypeEnums": [
          "Object",
          "Primitive",
          "String",
          "Primitive",
          "Primitive",
          "String",
          "String",
          "Primitive",
          "Primitive",
          "Object"
        ],
        "AdditionalInfos": [
          null,
          "Int32",
          null,
          "Int32",
          "Int32",
          null,
          null,
          "Boolean",
          "Boolean",
          null
        ]
      },
      "LibraryId": 2,
      "Values": [
        {
          "RecordTypeEnum": "ObjectNull"
        },
        0,
        {
          "ObjectId": 63,
          "Value": "::Leave.:: (3e12fa98-aff8-4e8a-8464-b7f8c6eba2dc)",
          "RecordTypeEnum": "BinaryObjectString"
        },
        0,
        1,
        {
          "IdRef": 7,
          "RecordTypeEnum": "MemberReference"
        },
        {
          "ObjectId": 65,
          "Value": "::Leave.::",
          "RecordTypeEnum": "BinaryObjectString"
        },
        false,
        false,
        {
          "RecordTypeEnum": "ObjectNull"
        }
      ],
      "RecordTypeEnum": "ClassWithMembersAndTypes"
    },
    {
      "ClassInfo": {
        "ObjectId": 49,
        "Name": "COC",
        "MemberCount": 4,
        "MemberNames": [
          "C:N",
          "CC:EC:Count",
          "CC:EC:0",
          "CC:EC:1"
        ]
      },
      "MemberTypeInfo": {
        "BinaryTypeEnums": [
          "Object",
          "Primitive",
          "Class",
          "Class"
        ],
        "AdditionalInfos": [
          null,
          "Int32",
          {
            "TypeName": "BC",
            "LibraryId": 2
          },
          {
            "TypeName": "BC",
            "LibraryId": 2
          }
        ]
      },
      "LibraryId": 2,
      "Values": [
        {
          "RecordTypeEnum": "ObjectNull"
        },
        2,
        {
          "IdRef": 66,
          "RecordTypeEnum": "MemberReference"
        },
        {
          "IdRef": 67,
          "RecordTypeEnum": "MemberReference"
        }
      ],
      "RecordTypeEnum": "ClassWithMembersAndTypes"
    },
    {
      "ClassInfo": {
        "ObjectId": 50,
        "Name": "Q",
        "MemberCount": 13,
        "MemberNames": [
          "CE:CC",
          "CE:PNS:Count",
          "CE:N",
          "SE:RA:Count",
          "SE:LT:Count",
          "SE:LT:0:Key",
          "SE:LT:0:Value",
          "Q:PA:Count",
          "Q:PA:0",
          "Q:PA:1",
          "Q:PA:2",
          "Q:Q",
          "Q:A"
        ]
      },
      "MemberTypeInfo": {
        "BinaryTypeEnums": [
          "Object",
          "Primitive",
          "String",
          "Primitive",
          "Primitive",
          "String",
          "String",
          "Primitive",
          "Class",
          "Class",
          "Class",
          "Class",
          "Class"
        ],
        "AdditionalInfos": [
          null,
          "Int32",
          null,
          "Int32",
          "Int32",
          null,
          null,
          "Int32",
          {
            "TypeName": "A3",
            "LibraryId": 2
          },
          {
            "TypeName": "A3",
            "LibraryId": 2
          },
          {
            "TypeName": "A3",
            "LibraryId": 2
          },
          {
            "TypeName": "A4",
            "LibraryId": 2
          },
          {
            "TypeName": "A4",
            "LibraryId": 2
          }
        ]
      },
      "LibraryId": 2,
      "Values": [
        {
          "RecordTypeEnum": "ObjectNull"
        },
        0,
        {
          "ObjectId": 68,
          "Value": " (ac05b266-3e53-4875-a1fb-07878f87f33d)*",
          "RecordTypeEnum": "BinaryObjectString"
        },
        0,
        1,
        {
          "IdRef": 27,
          "RecordTypeEnum": "MemberReference"
        },
        {
          "IdRef": 4,
          "RecordTypeEnum": "MemberReference"
        },
        3,
        {
          "IdRef": 71,
          "RecordTypeEnum": "MemberReference"
        },
        {
          "IdRef": 72,
          "RecordTypeEnum": "MemberReference"
        },
        {
          "IdRef": 73,
          "RecordTypeEnum": "MemberReference"
        },
        {
          "IdRef": 28,
          "RecordTypeEnum": "MemberReference"
        },
        {
          "IdRef": 29,
          "RecordTypeEnum": "MemberReference"
        }
      ],
      "RecordTypeEnum": "ClassWithMembersAndTypes"
    },
    {
      "ClassInfo": {
        "ObjectId": 56,
        "Name": "BC",
        "MemberCount": 4,
        "MemberNames": [
          "C:N",
          "CIC:P",
          "CIC:AD",
          "BC:V"
        ]
      },
      "MemberTypeInfo": {
        "BinaryTypeEnums": [
          "Object",
          "String",
          "Primitive",
          "Primitive"
        ],
        "AdditionalInfos": [
          null,
          null,
          "Boolean",
          "Boolean"
        ]
      },
      "LibraryId": 2,
      "Values": [
        {
          "RecordTypeEnum": "ObjectNull"
        },
        {
          "ObjectId": 76,
          "Value": "context.xpbl_deb_allBombsExploded",
          "RecordTypeEnum": "BinaryObjectString"
        },
        true,
        true
      ],
      "RecordTypeEnum": "ClassWithMembersAndTypes"
    },
    {
      "ObjectId": 57,
      "MetadataId": 56,
      "Values": [
        {
          "RecordTypeEnum": "ObjectNull"
        },
        {
          "ObjectId": 77,
          "Value": "context.xpbl_deb_consoleFixed",
          "RecordTypeEnum": "BinaryObjectString"
        },
        true,
        false
      ],
      "RecordTypeEnum": "ClassWithId"
    },
    {
      "ClassInfo": {
        "ObjectId": 58,
        "Name": "Q",
        "MemberCount": 12,
        "MemberNames": [
          "CE:CC",
          "CE:PNS:Count",
          "CE:N",
          "SE:RA:Count",
          "SE:RA:0",
          "SE:LT:Count",
          "SE:LT:0:Key",
          "SE:LT:0:Value",
          "Q:PA:Count",
          "Q:PA:0",
          "Q:Q",
          "Q:A"
        ]
      },
      "MemberTypeInfo": {
        "BinaryTypeEnums": [
          "Class",
          "Primitive",
          "String",
          "Primitive",
          "Class",
          "Primitive",
          "String",
          "String",
          "Primitive",
          "Class",
          "Class",
          "Class"
        ],
        "AdditionalInfos": [
          {
            "TypeName": "MPMSC",
            "LibraryId": 2
          },
          "Int32",
          null,
          "Int32",
          {
            "TypeName": "SBFV",
            "LibraryId": 2
          },
          "Int32",
          null,
          null,
          "Int32",
          {
            "TypeName": "A3",
            "LibraryId": 2
          },
          {
            "TypeName": "A4",
            "LibraryId": 2
          },
          {
            "TypeName": "A4",
            "LibraryId": 2
          }
        ]
      },
      "LibraryId": 2,
      "Values": [
        {
          "IdRef": 78,
          "RecordTypeEnum": "MemberReference"
        },
        0,
        {
          "ObjectId": 79,
          "Value": "::This computer's wiring is intuitively  (3a10b4cc-fbe1-4001-a1b9-520b095ed69b)",
          "RecordTypeEnum": "BinaryObjectString"
        },
        1,
        {
          "IdRef": 80,
          "RecordTypeEnum": "MemberReference"
        },
        1,
        {
          "IdRef": 7,
          "RecordTypeEnum": "MemberReference"
        },
        {
          "ObjectId": 82,
          "Value": "::This computer's wiring is intuitively designed in such a way that it makes it quite clear as to which cable powers what section. There are a dozen of cords heading towards the destroyed tankers and a few more dedicated to operating the rest of the ship. It would be a waste of time attempting to reestablish the connection with the oil containers, so you shift your focus on fixing the rest of the stuff. After a few minutes you job is done and the console can be powered up once more.::",
          "RecordTypeEnum": "BinaryObjectString"
        },
        1,
        {
          "IdRef": 83,
          "RecordTypeEnum": "MemberReference"
        },
        {
          "IdRef": 28,
          "RecordTypeEnum": "MemberReference"
        },
        {
          "IdRef": 29,
          "RecordTypeEnum": "MemberReference"
        }
      ],
      "RecordTypeEnum": "ClassWithMembersAndTypes"
    },
    {
      "ClassInfo": {
        "ObjectId": 59,
        "Name": "Q",
        "MemberCount": 11,
        "MemberNames": [
          "CE:CC",
          "CE:PNS:Count",
          "CE:N",
          "SE:RA:Count",
          "SE:LT:Count",
          "SE:LT:0:Key",
          "SE:LT:0:Value",
          "Q:PA:Count",
          "Q:PA:0",
          "Q:Q",
          "Q:A"
        ]
      },
      "MemberTypeInfo": {
        "BinaryTypeEnums": [
          "Object",
          "Primitive",
          "String",
          "Primitive",
          "Primitive",
          "String",
          "String",
          "Primitive",
          "Class",
          "Class",
          "Class"
        ],
        "AdditionalInfos": [
          null,
          "Int32",
          null,
          "Int32",
          "Int32",
          null,
          null,
          "Int32",
          {
            "TypeName": "A3",
            "LibraryId": 2
          },
          {
            "TypeName": "A4",
            "LibraryId": 2
          },
          {
            "TypeName": "A4",
            "LibraryId": 2
          }
        ]
      },
      "LibraryId": 2,
      "Values": [
        {
          "RecordTypeEnum": "ObjectNull"
        },
        0,
        {
          "ObjectId": 86,
          "Value": "::Despite the device's clear and relativ (aa6f95f8-ef6c-4af0-a349-3d897edbbab8)",
          "RecordTypeEnum": "BinaryObjectString"
        },
        0,
        1,
        {
          "IdRef": 6,
          "RecordTypeEnum": "MemberReference"
        },
        {
          "ObjectId": 88,
          "Value": "::Despite the device's clear and relatively simple design, the problem you're faced when it comes to repairing it is still too hard for you to solve.::",
          "RecordTypeEnum": "BinaryObjectString"
        },
        1,
        {
          "IdRef": 46,
          "RecordTypeEnum": "MemberReference"
        },
        {
          "IdRef": 28,
          "RecordTypeEnum": "MemberReference"
        },
        {
          "IdRef": 29,
          "RecordTypeEnum": "MemberReference"
        }
      ],
      "RecordTypeEnum": "ClassWithMembersAndTypes"
    },
    {
      "ObjectId": 66,
      "MetadataId": 56,
      "Values": [
        {
          "RecordTypeEnum": "ObjectNull"
        },
        {
          "ObjectId": 92,
          "Value": "context.xpbl_deb_allBombsExploded",
          "RecordTypeEnum": "BinaryObjectString"
        },
        true,
        false
      ],
      "RecordTypeEnum": "ClassWithId"
    },
    {
      "ObjectId": 67,
      "MetadataId": 56,
      "Values": [
        {
          "RecordTypeEnum": "ObjectNull"
        },
        {
          "ObjectId": 93,
          "Value": "context.xpbl_deb_consoleFixed",
          "RecordTypeEnum": "BinaryObjectString"
        },
        true,
        true
      ],
      "RecordTypeEnum": "ClassWithId"
    },
    {
      "ClassInfo": {
        "ObjectId": 71,
        "Name": "A3",
        "MemberCount": 11,
        "MemberNames": [
          "CE:CC",
          "CE:PNS:Count",
          "CE:PNS:0",
          "CE:N",
          "SE:RA:Count",
          "SE:LT:Count",
          "SE:LT:0:Key",
          "SE:LT:0:Value",
          "A3:ID",
          "A3:D",
          "A3:DC"
        ]
      },
      "MemberTypeInfo": {
        "BinaryTypeEnums": [
          "Class",
          "Primitive",
          "Class",
          "String",
          "Primitive",
          "Primitive",
          "String",
          "String",
          "Primitive",
          "Primitive",
          "Class"
        ],
        "AdditionalInfos": [
          {
            "TypeName": "CAC",
            "LibraryId": 2
          },
          "Int32",
          {
            "TypeName": "Q",
            "LibraryId": 2
          },
          null,
          "Int32",
          "Int32",
          null,
          null,
          "Boolean",
          "Boolean",
          {
            "TypeName": "BC",
            "LibraryId": 2
          }
        ]
      },
      "LibraryId": 2,
      "Values": [
        {
          "IdRef": 94,
          "RecordTypeEnum": "MemberReference"
        },
        1,
        {
          "IdRef": 95,
          "RecordTypeEnum": "MemberReference"
        },
        {
          "ObjectId": 96,
          "Value": "::Override manual control of tanker 1-3. (eea15792-b969-4791-bbba-d852ced38126)",
          "RecordTypeEnum": "BinaryObjectString"
        },
        0,
        1,
        {
          "IdRef": 27,
          "RecordTypeEnum": "MemberReference"
        },
        {
          "ObjectId": 98,
          "Value": "::Override manual control of tanker 1-3.::",
          "RecordTypeEnum": "BinaryObjectString"
        },
        false,
        false,
        {
          "IdRef": 99,
          "RecordTypeEnum": "MemberReference"
        }
      ],
      "RecordTypeEnum": "ClassWithMembersAndTypes"
    },
    {
      "ClassInfo": {
        "ObjectId": 72,
        "Name": "A3",
        "MemberCount": 11,
        "MemberNames": [
          "CE:CC",
          "CE:PNS:Count",
          "CE:PNS:0",
          "CE:N",
          "SE:RA:Count",
          "SE:LT:Count",
          "SE:LT:0:Key",
          "SE:LT:0:Value",
          "A3:ID",
          "A3:D",
          "A3:DC"
        ]
      },
      "MemberTypeInfo": {
        "BinaryTypeEnums": [
          "Class",
          "Primitive",
          "Class",
          "String",
          "Primitive",
          "Primitive",
          "String",
          "String",
          "Primitive",
          "Primitive",
          "Class"
        ],
        "AdditionalInfos": [
          {
            "TypeName": "BC",
            "LibraryId": 2
          },
          "Int32",
          {
            "TypeName": "Q",
            "LibraryId": 2
          },
          null,
          "Int32",
          "Int32",
          null,
          null,
          "Boolean",
          "Boolean",
          {
            "TypeName": "BC",
            "LibraryId": 2
          }
        ]
      },
      "LibraryId": 2,
      "Values": [
        {
          "IdRef": 100,
          "RecordTypeEnum": "MemberReference"
        },
        1,
        {
          "IdRef": 101,
          "RecordTypeEnum": "MemberReference"
        },
        {
          "ObjectId": 102,
          "Value": "::Unlock cargo.:: (74b0a2ff-cf27-43dd-aeb6-7a1a6ef8b10c)",
          "RecordTypeEnum": "BinaryObjectString"
        },
        0,
        1,
        {
          "IdRef": 9,
          "RecordTypeEnum": "MemberReference"
        },
        {
          "ObjectId": 104,
          "Value": "::Unlock cargo.::",
          "RecordTypeEnum": "BinaryObjectString"
        },
        false,
        false,
        {
          "IdRef": 105,
          "RecordTypeEnum": "MemberReference"
        }
      ],
      "RecordTypeEnum": "ClassWithMembersAndTypes"
    },
    {
      "ClassInfo": {
        "ObjectId": 73,
        "Name": "A3",
        "MemberCount": 10,
        "MemberNames": [
          "CE:CC",
          "CE:PNS:Count",
          "CE:N",
          "SE:RA:Count",
          "SE:LT:Count",
          "SE:LT:0:Key",
          "SE:LT:0:Value",
          "A3:ID",
          "A3:D",
          "A3:DC"
        ]
      },
      "MemberTypeInfo": {
        "BinaryTypeEnums": [
          "Object",
          "Primitive",
          "String",
          "Primitive",
          "Primitive",
          "String",
          "String",
          "Primitive",
          "Primitive",
          "Object"
        ],
        "AdditionalInfos": [
          null,
          "Int32",
          null,
          "Int32",
          "Int32",
          null,
          null,
          "Boolean",
          "Boolean",
          null
        ]
      },
      "LibraryId": 2,
      "Values": [
        {
          "RecordTypeEnum": "ObjectNull"
        },
        0,
        {
          "ObjectId": 106,
          "Value": "::Leave.:: (762e534a-7ed3-484d-b7d4-f22ed0e994d3)",
          "RecordTypeEnum": "BinaryObjectString"
        },
        0,
        1,
        {
          "IdRef": 27,
          "RecordTypeEnum": "MemberReference"
        },
        {
          "ObjectId": 108,
          "Value": "::Leave.::",
          "RecordTypeEnum": "BinaryObjectString"
        },
        false,
        false,
        {
          "RecordTypeEnum": "ObjectNull"
        }
      ],
      "RecordTypeEnum": "ClassWithMembersAndTypes"
    },
    {
      "ClassInfo": {
        "ObjectId": 78,
        "Name": "MPMSC",
        "MemberCount": 3,
        "MemberNames": [
          "C:N",
          "MPMSC:MV",
          "MPMSC:SN"
        ]
      },
      "MemberTypeInfo": {
        "BinaryTypeEnums": [
          "Object",
          "Primitive",
          "Class"
        ],
        "AdditionalInfos": [
          null,
          "Int32",
          {
            "TypeName": "eSKE",
            "LibraryId": 2
          }
        ]
      },
      "LibraryId": 2,
      "Values": [
        {
          "RecordTypeEnum": "ObjectNull"
        },
        85,
        {
          "ClassInfo": {
            "ObjectId": -109,
            "Name": "eSKE",
            "MemberCount": 1,
            "MemberNames": [
              "value__"
            ]
          },
          "MemberTypeInfo": {
            "BinaryTypeEnums": [
              "Primitive"
            ],
            "AdditionalInfos": [
              "Int32"
            ]
          },
          "LibraryId": 2,
          "Values": [
            31
          ],
          "RecordTypeEnum": "ClassWithMembersAndTypes"
        }
      ],
      "RecordTypeEnum": "ClassWithMembersAndTypes"
    },
    {
      "ClassInfo": {
        "ObjectId": 80,
        "Name": "SBFV",
        "MemberCount": 3,
        "MemberNames": [
          "BA:N",
          "SFVA:P",
          "SBFV:V"
        ]
      },
      "MemberTypeInfo": {
        "BinaryTypeEnums": [
          "String",
          "String",
          "Primitive"
        ],
        "AdditionalInfos": [
          null,
          null,
          "Boolean"
        ]
      },
      "LibraryId": 2,
      "Values": [
        {
          "ObjectId": 110,
          "Value": "997b9d9c-1b66-424c-9a57-682a683df705",
          "RecordTypeEnum": "BinaryObjectString"
        },
        {
          "ObjectId": 111,
          "Value": "context.xpbl_deb_consoleFixed",
          "RecordTypeEnum": "BinaryObjectString"
        },
        true
      ],
      "RecordTypeEnum": "ClassWithMembersAndTypes"
    },
    {
      "ClassInfo": {
        "ObjectId": 83,
        "Name": "A3",
        "MemberCount": 11,
        "MemberNames": [
          "CE:CC",
          "CE:PNS:Count",
          "CE:PNS:0",
          "CE:N",
          "SE:RA:Count",
          "SE:LT:Count",
          "SE:LT:0:Key",
          "SE:LT:0:Value",
          "A3:ID",
          "A3:D",
          "A3:DC"
        ]
      },
      "MemberTypeInfo": {
        "BinaryTypeEnums": [
          "Object",
          "Primitive",
          "Class",
          "String",
          "Primitive",
          "Primitive",
          "String",
          "String",
          "Primitive",
          "Primitive",
          "Object"
        ],
        "AdditionalInfos": [
          null,
          "Int32",
          {
            "TypeName": "Q",
            "LibraryId": 2
          },
          null,
          "Int32",
          "Int32",
          null,
          null,
          "Boolean",
          "Boolean",
          null
        ]
      },
      "LibraryId": 2,
      "Values": [
        {
          "RecordTypeEnum": "ObjectNull"
        },
        1,
        {
          "IdRef": 112,
          "RecordTypeEnum": "MemberReference"
        },
        {
          "ObjectId": 113,
          "Value": "::Start the computer.:: (12d71976-8106-49a7-9b46-e3b6cd7608f3)",
          "RecordTypeEnum": "BinaryObjectString"
        },
        0,
        1,
        {
          "IdRef": 7,
          "RecordTypeEnum": "MemberReference"
        },
        {
          "ObjectId": 115,
          "Value": "::Start the computer.::",
          "RecordTypeEnum": "BinaryObjectString"
        },
        false,
        false,
        {
          "RecordTypeEnum": "ObjectNull"
        }
      ],
      "RecordTypeEnum": "ClassWithMembersAndTypes"
    },
    {
      "ObjectId": 94,
      "MetadataId": 41,
      "Values": [
        {
          "RecordTypeEnum": "ObjectNull"
        },
        2,
        {
          "IdRef": 116,
          "RecordTypeEnum": "MemberReference"
        },
        {
          "IdRef": 117,
          "RecordTypeEnum": "MemberReference"
        }
      ],
      "RecordTypeEnum": "ClassWithId"
    },
    {
      "ClassInfo": {
        "ObjectId": 95,
        "Name": "Q",
        "MemberCount": 12,
        "MemberNames": [
          "CE:CC",
          "CE:PNS:Count",
          "CE:PNS:0",
          "CE:N",
          "SE:RA:Count",
          "SE:RA:0",
          "SE:LT:Count",
          "SE:LT:0:Key",
          "SE:LT:0:Value",
          "Q:PA:Count",
          "Q:Q",
          "Q:A"
        ]
      },
      "MemberTypeInfo": {
        "BinaryTypeEnums": [
          "Object",
          "Primitive",
          "Class",
          "String",
          "Primitive",
          "Class",
          "Primitive",
          "String",
          "String",
          "Primitive",
          "Class",
          "Class"
        ],
        "AdditionalInfos": [
          null,
          "Int32",
          {
            "TypeName": "Q",
            "LibraryId": 2
          },
          null,
          "Int32",
          {
            "TypeName": "EJA",
            "LibraryId": 2
          },
          "Int32",
          null,
          null,
          "Int32",
          {
            "TypeName": "A4",
            "LibraryId": 2
          },
          {
            "TypeName": "A4",
            "LibraryId": 2
          }
        ]
      },
      "LibraryId": 2,
      "Values": [
        {
          "RecordTypeEnum": "ObjectNull"
        },
        1,
        {
          "IdRef": 50,
          "RecordTypeEnum": "MemberReference"
        },
        {
          "ObjectId": 119,
          "Value": "::Access granted, valves are now manuall (bb4a7500-b9bf-47a7-a204-7c19d3cc38f4)*",
          "RecordTypeEnum": "BinaryObjectString"
        },
        1,
        {
          "IdRef": 120,
          "RecordTypeEnum": "MemberReference"
        },
        1,
        {
          "IdRef": 9,
          "RecordTypeEnum": "MemberReference"
        },
        {
          "ObjectId": 122,
          "Value": "::Access granted, valves are now manually operable.::",
          "RecordTypeEnum": "BinaryObjectString"
        },
        0,
        {
          "IdRef": 28,
          "RecordTypeEnum": "MemberReference"
        },
        {
          "IdRef": 29,
          "RecordTypeEnum": "MemberReference"
        }
      ],
      "RecordTypeEnum": "ClassWithMembersAndTypes"
    },
    {
      "ObjectId": 99,
      "MetadataId": 56,
      "Values": [
        {
          "RecordTypeEnum": "ObjectNull"
        },
        {
          "ObjectId": 125,
          "Value": "xpbl_deb_valveAccessGranted",
          "RecordTypeEnum": "BinaryObjectString"
        },
        true,
        true
      ],
      "RecordTypeEnum": "ClassWithId"
    },
    {
      "ObjectId": 100,
      "MetadataId": 56,
      "Values": [
        {
          "RecordTypeEnum": "ObjectNull"
        },
        {
          "ObjectId": 126,
          "Value": "context.xpbl_deb_boxAccessGranted",
          "RecordTypeEnum": "BinaryObjectString"
        },
        true,
        false
      ],
      "RecordTypeEnum": "ClassWithId"
    },
    {
      "ClassInfo": {
        "ObjectId": 101,
        "Name": "Q",
        "MemberCount": 13,
        "MemberNames": [
          "CE:CC",
          "CE:PNS:Count",
          "CE:N",
          "SE:RA:Count",
          "SE:LT:Count",
          "SE:LT:0:Key",
          "SE:LT:0:Value",
          "Q:PA:Count",
          "Q:PA:0",
          "Q:PA:1",
          "Q:PA:2",
          "Q:Q",
          "Q:A"
        ]
      },
      "MemberTypeInfo": {
        "BinaryTypeEnums": [
          "Object",
          "Primitive",
          "String",
          "Primitive",
          "Primitive",
          "String",
          "String",
          "Primitive",
          "Class",
          "Class",
          "Class",
          "Class",
          "Class"
        ],
        "AdditionalInfos": [
          null,
          "Int32",
          null,
          "Int32",
          "Int32",
          null,
          null,
          "Int32",
          {
            "TypeName": "A3",
            "LibraryId": 2
          },
          {
            "TypeName": "A3",
            "LibraryId": 2
          },
          {
            "TypeName": "A3",
            "LibraryId": 2
          },
          {
            "TypeName": "A4",
            "LibraryId": 2
          },
          {
            "TypeName": "A4",
            "LibraryId": 2
          }
        ]
      },
      "LibraryId": 2,
      "Values": [
        {
          "RecordTypeEnum": "ObjectNull"
        },
        0,
        {
          "ObjectId": 127,
          "Value": "::Please insert the correct password.:: (3a9756bd-5a6b-4f77-9095-df47e21e4bda)",
          "RecordTypeEnum": "BinaryObjectString"
        },
        0,
        1,
        {
          "IdRef": 9,
          "RecordTypeEnum": "MemberReference"
        },
        {
          "ObjectId": 129,
          "Value": "::Please insert the correct password.::",
          "RecordTypeEnum": "BinaryObjectString"
        },
        3,
        {
          "IdRef": 130,
          "RecordTypeEnum": "MemberReference"
        },
        {
          "IdRef": 131,
          "RecordTypeEnum": "MemberReference"
        },
        {
          "IdRef": 132,
          "RecordTypeEnum": "MemberReference"
        },
        {
          "IdRef": 28,
          "RecordTypeEnum": "MemberReference"
        },
        {
          "IdRef": 29,
          "RecordTypeEnum": "MemberReference"
        }
      ],
      "RecordTypeEnum": "ClassWithMembersAndTypes"
    },
    {
      "ObjectId": 105,
      "MetadataId": 56,
      "Values": [
        {
          "RecordTypeEnum": "ObjectNull"
        },
        {
          "ObjectId": 135,
          "Value": "xpbl_deb_boxAccessGranted",
          "RecordTypeEnum": "BinaryObjectString"
        },
        true,
        true
      ],
      "RecordTypeEnum": "ClassWithId"
    },
    {
      "ClassInfo": {
        "ObjectId": 112,
        "Name": "Q",
        "MemberCount": 11,
        "MemberNames": [
          "CE:CC",
          "CE:PNS:Count",
          "CE:PNS:0",
          "CE:N",
          "SE:RA:Count",
          "SE:LT:Count",
          "SE:LT:0:Key",
          "SE:LT:0:Value",
          "Q:PA:Count",
          "Q:Q",
          "Q:A"
        ]
      },
      "MemberTypeInfo": {
        "BinaryTypeEnums": [
          "Object",
          "Primitive",
          "Class",
          "String",
          "Primitive",
          "Primitive",
          "String",
          "String",
          "Primitive",
          "Class",
          "Class"
        ],
        "AdditionalInfos": [
          null,
          "Int32",
          {
            "TypeName": "Q",
            "LibraryId": 2
          },
          null,
          "Int32",
          "Int32",
          null,
          null,
          "Int32",
          {
            "TypeName": "A4",
            "LibraryId": 2
          },
          {
            "TypeName": "A4",
            "LibraryId": 2
          }
        ]
      },
      "LibraryId": 2,
      "Values": [
        {
          "RecordTypeEnum": "ObjectNull"
        },
        1,
        {
          "IdRef": 50,
          "RecordTypeEnum": "MemberReference"
        },
        {
          "ObjectId": 137,
          "Value": "::Cruise control.Maneuvering thrusters o (cdad09c7-2678-46ba-b034-fb81a95af34d)*",
          "RecordTypeEnum": "BinaryObjectString"
        },
        0,
        1,
        {
          "IdRef": 7,
          "RecordTypeEnum": "MemberReference"
        },
        {
          "ObjectId": 139,
          "Value": "::Cruise control.\r\n\r\nManeuvering thrusters offline. Missing readings from tanker sections 1-3.::",
          "RecordTypeEnum": "BinaryObjectString"
        },
        0,
        {
          "IdRef": 28,
          "RecordTypeEnum": "MemberReference"
        },
        {
          "IdRef": 29,
          "RecordTypeEnum": "MemberReference"
        }
      ],
      "RecordTypeEnum": "ClassWithMembersAndTypes"
    },
    {
      "ObjectId": 116,
      "MetadataId": 56,
      "Values": [
        {
          "RecordTypeEnum": "ObjectNull"
        },
        {
          "ObjectId": 142,
          "Value": "context.xpbl_deb_valveAccessGranted",
          "RecordTypeEnum": "BinaryObjectString"
        },
        true,
        false
      ],
      "RecordTypeEnum": "ClassWithId"
    },
    {
      "ObjectId": 117,
      "MetadataId": 56,
      "Values": [
        {
          "RecordTypeEnum": "ObjectNull"
        },
        {
          "ObjectId": 143,
          "Value": "xpbl_deb_allBombsExploded",
          "RecordTypeEnum": "BinaryObjectString"
        },
        true,
        false
      ],
      "RecordTypeEnum": "ClassWithId"
    },
    {
      "ClassInfo": {
        "ObjectId": 120,
        "Name": "EJA",
        "MemberCount": 2,
        "MemberNames": [
          "BA:N",
          "EJA:J"
        ]
      },
      "MemberTypeInfo": {
        "BinaryTypeEnums": [
          "String",
          "Class"
        ],
        "AdditionalInfos": [
          null,
          {
            "TypeName": "XJL",
            "LibraryId": 2
          }
        ]
      },
      "LibraryId": 2,
      "Values": [
        {
          "ObjectId": 144,
          "Value": "93bf194d-d5db-4088-b762-6fe904702e6c",
          "RecordTypeEnum": "BinaryObjectString"
        },
        {
          "IdRef": 145,
          "RecordTypeEnum": "MemberReference"
        }
      ],
      "RecordTypeEnum": "ClassWithMembersAndTypes"
    },
    {
      "ClassInfo": {
        "ObjectId": 130,
        "Name": "A3",
        "MemberCount": 11,
        "MemberNames": [
          "CE:CC",
          "CE:PNS:Count",
          "CE:PNS:0",
          "CE:N",
          "SE:RA:Count",
          "SE:LT:Count",
          "SE:LT:0:Key",
          "SE:LT:0:Value",
          "A3:ID",
          "A3:D",
          "A3:DC"
        ]
      },
      "MemberTypeInfo": {
        "BinaryTypeEnums": [
          "Class",
          "Primitive",
          "Class",
          "String",
          "Primitive",
          "Primitive",
          "String",
          "String",
          "Primitive",
          "Primitive",
          "Object"
        ],
        "AdditionalInfos": [
          {
            "TypeName": "BC",
            "LibraryId": 2
          },
          "Int32",
          {
            "TypeName": "Q",
            "LibraryId": 2
          },
          null,
          "Int32",
          "Int32",
          null,
          null,
          "Boolean",
          "Boolean",
          null
        ]
      },
      "LibraryId": 2,
      "Values": [
        {
          "IdRef": 146,
          "RecordTypeEnum": "MemberReference"
        },
        1,
        {
          "IdRef": 147,
          "RecordTypeEnum": "MemberReference"
        },
        {
          "ObjectId": 148,
          "Value": "::Insert: Coxswain.:: (5f18ac7a-3c96-47a5-87f2-d82340b32325)",
          "RecordTypeEnum": "BinaryObjectString"
        },
        0,
        1,
        {
          "IdRef": 9,
          "RecordTypeEnum": "MemberReference"
        },
        {
          "ObjectId": 150,
          "Value": "::Insert: Coxswain.::",
          "RecordTypeEnum": "BinaryObjectString"
        },
        false,
        false,
        {
          "RecordTypeEnum": "ObjectNull"
        }
      ],
      "RecordTypeEnum": "ClassWithMembersAndTypes"
    },
    {
      "ClassInfo": {
        "ObjectId": 131,
        "Name": "A3",
        "MemberCount": 11,
        "MemberNames": [
          "CE:CC",
          "CE:PNS:Count",
          "CE:PNS:0",
          "CE:N",
          "SE:RA:Count",
          "SE:LT:Count",
          "SE:LT:0:Key",
          "SE:LT:0:Value",
          "A3:ID",
          "A3:D",
          "A3:DC"
        ]
      },
      "MemberTypeInfo": {
        "BinaryTypeEnums": [
          "Object",
          "Primitive",
          "Class",
          "String",
          "Primitive",
          "Primitive",
          "String",
          "String",
          "Primitive",
          "Primitive",
          "Object"
        ],
        "AdditionalInfos": [
          null,
          "Int32",
          {
            "TypeName": "Q",
            "LibraryId": 2
          },
          null,
          "Int32",
          "Int32",
          null,
          null,
          "Boolean",
          "Boolean",
          null
        ]
      },
      "LibraryId": 2,
      "Values": [
        {
          "RecordTypeEnum": "ObjectNull"
        },
        1,
        {
          "IdRef": 151,
          "RecordTypeEnum": "MemberReference"
        },
        {
          "ObjectId": 152,
          "Value": "::Try something random.:: (2e1b277d-27ba-4087-8a6e-2d1edb85af26)",
          "RecordTypeEnum": "BinaryObjectString"
        },
        0,
        1,
        {
          "IdRef": 9,
          "RecordTypeEnum": "MemberReference"
        },
        {
          "ObjectId": 154,
          "Value": "::Try something random.::",
          "RecordTypeEnum": "BinaryObjectString"
        },
        false,
        false,
        {
          "RecordTypeEnum": "ObjectNull"
        }
      ],
      "RecordTypeEnum": "ClassWithMembersAndTypes"
    },
    {
      "ClassInfo": {
        "ObjectId": 132,
        "Name": "A3",
        "MemberCount": 10,
        "MemberNames": [
          "CE:CC",
          "CE:PNS:Count",
          "CE:N",
          "SE:RA:Count",
          "SE:LT:Count",
          "SE:LT:0:Key",
          "SE:LT:0:Value",
          "A3:ID",
          "A3:D",
          "A3:DC"
        ]
      },
      "MemberTypeInfo": {
        "BinaryTypeEnums": [
          "Object",
          "Primitive",
          "String",
          "Primitive",
          "Primitive",
          "String",
          "String",
          "Primitive",
          "Primitive",
          "Object"
        ],
        "AdditionalInfos": [
          null,
          "Int32",
          null,
          "Int32",
          "Int32",
          null,
          null,
          "Boolean",
          "Boolean",
          null
        ]
      },
      "LibraryId": 2,
      "Values": [
        {
          "RecordTypeEnum": "ObjectNull"
        },
        0,
        {
          "ObjectId": 155,
          "Value": "::Leave.:: (380bbdc6-9a78-4668-8116-687ddef4b66e)",
          "RecordTypeEnum": "BinaryObjectString"
        },
        0,
        1,
        {
          "IdRef": 9,
          "RecordTypeEnum": "MemberReference"
        },
        {
          "ObjectId": 157,
          "Value": "::Leave.::",
          "RecordTypeEnum": "BinaryObjectString"
        },
        false,
        false,
        {
          "RecordTypeEnum": "ObjectNull"
        }
      ],
      "RecordTypeEnum": "ClassWithMembersAndTypes"
    },
    {
      "ClassInfo": {
        "ObjectId": 145,
        "Name": "XJL",
        "MemberCount": 2,
        "MemberNames": [
          "J1:N",
          "XJL:J"
        ]
      },
      "MemberTypeInfo": {
        "BinaryTypeEnums": [
          "Object",
          "String"
        ],
        "AdditionalInfos": [
          null,
          null
        ]
      },
      "LibraryId": 2,
      "Values": [
        {
          "RecordTypeEnum": "ObjectNull"
        },
        {
          "ObjectId": 158,
          "Value": "XPBLDEBJDTUV",
          "RecordTypeEnum": "BinaryObjectString"
        }
      ],
      "RecordTypeEnum": "ClassWithMembersAndTypes"
    },
    {
      "ObjectId": 146,
      "MetadataId": 56,
      "Values": [
        {
          "RecordTypeEnum": "ObjectNull"
        },
        {
          "ObjectId": 159,
          "Value": "context.xpbl_deb_boxPasswordKnown",
          "RecordTypeEnum": "BinaryObjectString"
        },
        true,
        true
      ],
      "RecordTypeEnum": "ClassWithId"
    },
    {
      "ClassInfo": {
        "ObjectId": 147,
        "Name": "Q",
        "MemberCount": 12,
        "MemberNames": [
          "CE:CC",
          "CE:PNS:Count",
          "CE:N",
          "SE:RA:Count",
          "SE:RA:0",
          "SE:LT:Count",
          "SE:LT:0:Key",
          "SE:LT:0:Value",
          "Q:PA:Count",
          "Q:PA:0",
          "Q:Q",
          "Q:A"
        ]
      },
      "MemberTypeInfo": {
        "BinaryTypeEnums": [
          "Object",
          "Primitive",
          "String",
          "Primitive",
          "Class",
          "Primitive",
          "String",
          "String",
          "Primitive",
          "Class",
          "Class",
          "Class"
        ],
        "AdditionalInfos": [
          null,
          "Int32",
          null,
          "Int32",
          {
            "TypeName": "EJA",
            "LibraryId": 2
          },
          "Int32",
          null,
          null,
          "Int32",
          {
            "TypeName": "A3",
            "LibraryId": 2
          },
          {
            "TypeName": "A4",
            "LibraryId": 2
          },
          {
            "TypeName": "A4",
            "LibraryId": 2
          }
        ]
      },
      "LibraryId": 2,
      "Values": [
        {
          "RecordTypeEnum": "ObjectNull"
        },
        0,
        {
          "ObjectId": 160,
          "Value": "::Cargo unlocked.:: (7ef06abf-1036-43cf-b63e-d960db5aa365)",
          "RecordTypeEnum": "BinaryObjectString"
        },
        1,
        {
          "IdRef": 161,
          "RecordTypeEnum": "MemberReference"
        },
        1,
        {
          "IdRef": 9,
          "RecordTypeEnum": "MemberReference"
        },
        {
          "ObjectId": 163,
          "Value": "::Cargo unlocked.::",
          "RecordTypeEnum": "BinaryObjectString"
        },
        1,
        {
          "IdRef": 132,
          "RecordTypeEnum": "MemberReference"
        },
        {
          "IdRef": 28,
          "RecordTypeEnum": "MemberReference"
        },
        {
          "IdRef": 29,
          "RecordTypeEnum": "MemberReference"
        }
      ],
      "RecordTypeEnum": "ClassWithMembersAndTypes"
    },
    {
      "ClassInfo": {
        "ObjectId": 151,
        "Name": "Q",
        "MemberCount": 11,
        "MemberNames": [
          "CE:CC",
          "CE:PNS:Count",
          "CE:PNS:0",
          "CE:N",
          "SE:RA:Count",
          "SE:LT:Count",
          "SE:LT:0:Key",
          "SE:LT:0:Value",
          "Q:PA:Count",
          "Q:Q",
          "Q:A"
        ]
      },
      "MemberTypeInfo": {
        "BinaryTypeEnums": [
          "Object",
          "Primitive",
          "Class",
          "String",
          "Primitive",
          "Primitive",
          "String",
          "String",
          "Primitive",
          "Class",
          "Class"
        ],
        "AdditionalInfos": [
          null,
          "Int32",
          {
            "TypeName": "Q",
            "LibraryId": 2
          },
          null,
          "Int32",
          "Int32",
          null,
          null,
          "Int32",
          {
            "TypeName": "A4",
            "LibraryId": 2
          },
          {
            "TypeName": "A4",
            "LibraryId": 2
          }
        ]
      },
      "LibraryId": 2,
      "Values": [
        {
          "RecordTypeEnum": "ObjectNull"
        },
        1,
        {
          "IdRef": 101,
          "RecordTypeEnum": "MemberReference"
        },
        {
          "ObjectId": 168,
          "Value": "::Wrong password.:: (eaf7b5fa-5cb4-471a-8153-6e430cc182e2)*",
          "RecordTypeEnum": "BinaryObjectString"
        },
        0,
        1,
        {
          "IdRef": 9,
          "RecordTypeEnum": "MemberReference"
        },
        {
          "ObjectId": 170,
          "Value": "::Wrong password.::\r\n\r\n",
          "RecordTypeEnum": "BinaryObjectString"
        },
        0,
        {
          "IdRef": 28,
          "RecordTypeEnum": "MemberReference"
        },
        {
          "IdRef": 29,
          "RecordTypeEnum": "MemberReference"
        }
      ],
      "RecordTypeEnum": "ClassWithMembersAndTypes"
    },
    {
      "ObjectId": 161,
      "MetadataId": 120,
      "Values": [
        {
          "ObjectId": 173,
          "Value": "02c16c29-743d-40e7-b5c3-30bd30863ad6",
          "RecordTypeEnum": "BinaryObjectString"
        },
        {
          "IdRef": 174,
          "RecordTypeEnum": "MemberReference"
        }
      ],
      "RecordTypeEnum": "ClassWithId"
    },
    {
      "ObjectId": 174,
      "MetadataId": 145,
      "Values": [
        {
          "RecordTypeEnum": "ObjectNull"
        },
        {
          "ObjectId": 175,
          "Value": "XPBLDEBJDTUB",
          "RecordTypeEnum": "BinaryObjectString"
        }
      ],
      "RecordTypeEnum": "ClassWithId"
    },
    {
      "RecordTypeEnum": "MessageEnd"
    }
  ]
}