{
  "Header": "F9538B831F363243BAAE0D17865D08544BF14C3141000000",
  "Records": [
    {
      "RootId": 1,
      "HeaderId": -1,
      "MajorVersion": 1,
      "MinorVersion": 0,
      "RecordTypeEnum": "SerializedStreamHeader"
    },
    {
      "LibraryId": 2,
      "LibraryName": "X",
      "RecordTypeEnum": "BinaryLibrary"
    },
    {
      "ClassInfo": {
        "ObjectId": 1,
        "Name": "DM",
        "MemberCount": 13,
        "MemberNames": [
          "DM:DN",
          "DM:DD",
          "DM:SE",
          "DM:LL:Count",
          "DM:LL:0",
          "DM:LL:1",
          "DM:LL:2",
          "DM:LL:3",
          "DM:A:Count",
          "DM:A:0",
          "DM:A:1",
          "DM:IC",
          "DM:P"
        ]
      },
      "MemberTypeInfo": {
        "BinaryTypeEnums": [
          "String",
          "Object",
          "Class",
          "Primitive",
          "String",
          "String",
          "String",
          "String",
          "Primitive",
          "Class",
          "Class",
          "Primitive",
          "Primitive"
        ],
        "AdditionalInfos": [
          null,
          null,
          {
            "TypeName": "J",
            "LibraryId": 2
          },
          "Int32",
          null,
          null,
          null,
          null,
          "Int32",
          {
            "TypeName": "A4",
            "LibraryId": 2
          },
          {
            "TypeName": "A4",
            "LibraryId": 2
          },
          "Boolean",
          "Boolean"
        ]
      },
      "LibraryId": 2,
      "Values": [
        {
          "ObjectId": 3,
          "Value": "tch_ref2",
          "RecordTypeEnum": "BinaryObjectString"
        },
        {
          "RecordTypeEnum": "ObjectNull"
        },
        {
          "IdRef": 4,
          "RecordTypeEnum": "MemberReference"
        },
        4,
        {
          "ObjectId": 5,
          "Value": "English",
          "RecordTypeEnum": "BinaryObjectString"
        },
        {
          "ObjectId": 6,
          "Value": "English",
          "RecordTypeEnum": "BinaryObjectString"
        },
        {
          "ObjectId": 7,
          "Value": "English",
          "RecordTypeEnum": "BinaryObjectString"
        },
        {
          "ObjectId": 8,
          "Value": "English",
          "RecordTypeEnum": "BinaryObjectString"
        },
        2,
        {
          "IdRef": 9,
          "RecordTypeEnum": "MemberReference"
        },
        {
          "IdRef": 10,
          "RecordTypeEnum": "MemberReference"
        },
        true,
        false
      ],
      "RecordTypeEnum": "ClassWithMembersAndTypes"
    },
    {
      "ClassInfo": {
        "ObjectId": 4,
        "Name": "J",
        "MemberCount": 5,
        "MemberNames": [
          "CE:CC",
          "CE:PNS:Count",
          "CE:PNS:0",
          "CE:PNS:1",
          "CE:N"
        ]
      },
      "MemberTypeInfo": {
        "BinaryTypeEnums": [
          "Object",
          "Primitive",
          "Class",
          "Class",
          "String"
        ],
        "AdditionalInfos": [
          null,
          "Int32",
          {
            "TypeName": "Q",
            "LibraryId": 2
          },
          {
            "TypeName": "Q",
            "LibraryId": 2
          },
          null
        ]
      },
      "LibraryId": 2,
      "Values": [
        {
          "RecordTypeEnum": "ObjectNull"
        },
        2,
        {
          "IdRef": 11,
          "RecordTypeEnum": "MemberReference"
        },
        {
          "IdRef": 12,
          "RecordTypeEnum": "MemberReference"
        },
        {
          "ObjectId": 13,
          "Value": "Start Element",
          "RecordTypeEnum": "BinaryObjectString"
        }
      ],
      "RecordTypeEnum": "ClassWithMembersAndTypes"
    },
    {
      "ClassInfo": {
        "ObjectId": 9,
        "Name": "A4",
        "MemberCount": 2,
        "MemberNames": [
          "A4:N",
          "A4:P"
        ]
      },
      "MemberTypeInfo": {
        "BinaryTypeEnums": [
          "String",
          "Object"
        ],
        "AdditionalInfos": [
          null,
          null
        ]
      },
      "LibraryId": 2,
      "Values": [
        {
          "ObjectId": 14,
          "Value": "speaker",
          "RecordTypeEnum": "BinaryObjectString"
        },
        {
          "RecordTypeEnum": "ObjectNull"
        }
      ],
      "RecordTypeEnum": "ClassWithMembersAndTypes"
    },
    {
      "ObjectId": 10,
      "MetadataId": 9,
      "Values": [
        {
          "ObjectId": 15,
          "Value": "player",
          "RecordTypeEnum": "BinaryObjectString"
        },
        {
          "RecordTypeEnum": "ObjectNull"
        }
      ],
      "RecordTypeEnum": "ClassWithId"
    },
    {
      "ClassInfo": {
        "ObjectId": 11,
        "Name": "Q",
        "MemberCount": 10,
        "MemberNames": [
          "CE:CC",
          "CE:PNS:Count",
          "CE:N",
          "SE:RA:Count",
          "SE:LT:Count",
          "SE:LT:0:Key",
          "SE:LT:0:Value",
          "Q:PA:Count",
          "Q:Q",
          "Q:A"
        ]
      },
      "MemberTypeInfo": {
        "BinaryTypeEnums": [
          "Class",
          "Primitive",
          "String",
          "Primitive",
          "Primitive",
          "String",
          "String",
          "Primitive",
          "Class",
          "Class"
        ],
        "AdditionalInfos": [
          {
            "TypeName": "BC",
            "LibraryId": 2
          },
          "Int32",
          null,
          "Int32",
          "Int32",
          null,
          null,
          "Int32",
          {
            "TypeName": "A4",
            "LibraryId": 2
          },
          {
            "TypeName": "A4",
            "LibraryId": 2
          }
        ]
      },
      "LibraryId": 2,
      "Values": [
        {
          "IdRef": 16,
          "RecordTypeEnum": "MemberReference"
        },
        0,
        {
          "ObjectId": 17,
          "Value": "We must resist the Faceless! (df300c10-7c3a-481a-9617-0278df482108)",
          "RecordTypeEnum": "BinaryObjectString"
        },
        0,
        1,
        {
          "IdRef": 7,
          "RecordTypeEnum": "MemberReference"
        },
        {
          "ObjectId": 19,
          "Value": "We must resist the Faceless!",
          "RecordTypeEnum": "BinaryObjectString"
        },
        0,
        {
          "IdRef": 9,
          "RecordTypeEnum": "MemberReference"
        },
        {
          "IdRef": 10,
          "RecordTypeEnum": "MemberReference"
        }
      ],
      "RecordTypeEnum": "ClassWithMembersAndTypes"
    },
    {
      "ClassInfo": {
        "ObjectId": 12,
        "Name": "Q",
        "MemberCount": 18,
        "MemberNames": [
          "CE:CC",
          "CE:PNS:Count",
          "CE:PNS:0",
          "CE:PNS:1",
          "CE:PNS:2",
          "CE:PNS:3",
          "CE:PNS:4",
          "CE:PNS:5",
          "CE:PNS:6",
          "CE:N",
          "SE:RA:Count",
          "SE:RA:0",
          "SE:LT:Count",
          "SE:LT:0:Key",
          "SE:LT:0:Value",
          "Q:PA:Count",
          "Q:Q",
          "Q:A"
        ]
      },
      "MemberTypeInfo": {
        "BinaryTypeEnums": [
          "Object",
          "Primitive",
          "Class",
          "Class",
          "Class",
          "Class",
          "Class",
          "Class",
          "Class",
          "String",
          "Primitive",
          "Class",
          "Primitive",
          "String",
          "String",
          "Primitive",
          "Class",
          "Class"
        ],
        "AdditionalInfos": [
          null,
          "Int32",
          {
            "TypeName": "Q",
            "LibraryId": 2
          },
          {
            "TypeName": "Q",
            "LibraryId": 2
          },
          {
            "TypeName": "Q",
            "LibraryId": 2
          },
          {
            "TypeName": "Q",
            "LibraryId": 2
          },
          {
            "TypeName": "Q",
            "LibraryId": 2
          },
          {
            "TypeName": "Q",
            "LibraryId": 2
          },
          {
            "TypeName": "Q",
            "LibraryId": 2
          },
          null,
          "Int32",
          {
            "TypeName": "FAPA",
            "LibraryId": 2
          },
          "Int32",
          null,
          null,
          "Int32",
          {
            "TypeName": "A4",
            "LibraryId": 2
          },
          {
            "TypeName": "A4",
            "LibraryId": 2
          }
        ]
      },
      "LibraryId": 2,
      "Values": [
        {
          "RecordTypeEnum": "ObjectNull"
        },
        7,
        {
          "IdRef": 22,
          "RecordTypeEnum": "MemberReference"
        },
        {
          "IdRef": 23,
          "RecordTypeEnum": "MemberReference"
        },
        {
          "IdRef": 24,
          "RecordTypeEnum": "MemberReference"
        },
        {
          "IdRef": 25,
          "RecordTypeEnum": "MemberReference"
        },
        {
          "IdRef": 26,
          "RecordTypeEnum": "MemberReference"
        },
        {
          "IdRef": 27,
          "RecordTypeEnum": "MemberReference"
        },
        {
          "IdRef": 28,
          "RecordTypeEnum": "MemberReference"
        },
        {
          "ObjectId": 29,
          "Value": " (20dbd11c-4a52-42c7-90bb-c18db1130d46)*",
          "RecordTypeEnum": "BinaryObjectString"
        },
        1,
        {
          "IdRef": 30,
          "RecordTypeEnum": "MemberReference"
        },
        1,
        {
          "IdRef": 8,
          "RecordTypeEnum": "MemberReference"
        },
        {
          "ObjectId": 32,
          "Value": "",
          "RecordTypeEnum": "BinaryObjectString"
        },
        0,
        {
          "IdRef": 9,
          "RecordTypeEnum": "MemberReference"
        },
        {
          "IdRef": 10,
          "RecordTypeEnum": "MemberReference"
        }
      ],
      "RecordTypeEnum": "ClassWithMembersAndTypes"
    },
    {
      "ClassInfo": {
        "ObjectId": 16,
        "Name": "BC",
        "MemberCount": 4,
        "MemberNames": [
          "C:N",
          "CIC:P",
          "CIC:AD",
          "BC:V"
        ]
      },
      "MemberTypeInfo": {
        "BinaryTypeEnums": [
          "Object",
          "String",
          "Primitive",
          "Primitive"
        ],
        "AdditionalInfos": [
          null,
          null,
          "Boolean",
          "Boolean"
        ]
      },
      "LibraryId": 2,
      "Values": [
        {
          "RecordTypeEnum": "ObjectNull"
        },
        {
          "ObjectId": 35,
          "Value": "context.loc_tch_invasionStarted",
          "RecordTypeEnum": "BinaryObjectString"
        },
        true,
        true
      ],
      "RecordTypeEnum": "ClassWithMembersAndTypes"
    },
    {
      "ClassInfo": {
        "ObjectId": 22,
        "Name": "Q",
        "MemberCount": 10,
        "MemberNames": [
          "CE:CC",
          "CE:PNS:Count",
          "CE:N",
          "SE:RA:Count",
          "SE:LT:Count",
          "SE:LT:0:Key",
          "SE:LT:0:Value",
          "Q:PA:Count",
          "Q:Q",
          "Q:A"
        ]
      },
      "MemberTypeInfo": {
        "BinaryTypeEnums": [
          "Object",
          "Primitive",
          "String",
          "Primitive",
          "Primitive",
          "String",
          "String",
          "Primitive",
          "Class",
          "Class"
        ],
        "AdditionalInfos": [
          null,
          "Int32",
          null,
          "Int32",
          "Int32",
          null,
          null,
          "Int32",
          {
            "TypeName": "A4",
            "LibraryId": 2
          },
          {
            "TypeName": "A4",
            "LibraryId": 2
          }
        ]
      },
      "LibraryId": 2,
      "Values": [
        {
          "RecordTypeEnum": "ObjectNull"
        },
        0,
        {
          "ObjectId": 36,
          "Value": "Tchort is evolution. (436a80bc-7269-4448-af82-9268951d2a90)",
          "RecordTypeEnum": "BinaryObjectString"
        },
        0,
        1,
        {
          "IdRef": 8,
          "RecordTypeEnum": "MemberReference"
        },
        {
          "ObjectId": 38,
          "Value": "Tchort is evolution.",
          "RecordTypeEnum": "BinaryObjectString"
        },
        0,
        {
          "IdRef": 9,
          "RecordTypeEnum": "MemberReference"
        },
        {
          "IdRef": 10,
          "RecordTypeEnum": "MemberReference"
        }
      ],
      "RecordTypeEnum": "ClassWithMembersAndTypes"
    },
    {
      "ClassInfo": {
        "ObjectId": 23,
        "Name": "Q",
        "MemberCount": 10,
        "MemberNames": [
          "CE:CC",
          "CE:PNS:Count",
          "CE:N",
          "SE:RA:Count",
          "SE:LT:Count",
          "SE:LT:0:Key",
          "SE:LT:0:Value",
          "Q:PA:Count",
          "Q:Q",
          "Q:A"
        ]
      },
      "MemberTypeInfo": {
        "BinaryTypeEnums": [
          "Object",
          "Primitive",
          "String",
          "Primitive",
          "Primitive",
          "String",
          "String",
          "Primitive",
          "Class",
          "Class"
        ],
        "AdditionalInfos": [
          null,
          "Int32",
          null,
          "Int32",
          "Int32",
          null,
          null,
          "Int32",
          {
            "TypeName": "A4",
            "LibraryId": 2
          },
          {
            "TypeName": "A4",
            "LibraryId": 2
          }
        ]
      },
      "LibraryId": 2,
      "Values": [
        {
          "RecordTypeEnum": "ObjectNull"
        },
        0,
        {
          "ObjectId": 41,
          "Value": "Refectory is a place to sit down and rel (4f4c2df9-7be7-4ea5-a425-4b8371cf7cea)",
          "RecordTypeEnum": "BinaryObjectString"
        },
        0,
        1,
        {
          "IdRef": 8,
          "RecordTypeEnum": "MemberReference"
        },
        {
          "ObjectId": 43,
          "Value": "Refectory is a place to sit down and relax... and enjoy your meal.",
          "RecordTypeEnum": "BinaryObjectString"
        },
        0,
        {
          "IdRef": 9,
          "RecordTypeEnum": "MemberReference"
        },
        {
          "IdRef": 10,
          "RecordTypeEnum": "MemberReference"
        }
      ],
      "RecordTypeEnum": "ClassWithMembersAndTypes"
    },
    {
      "ClassInfo": {
        "ObjectId": 24,
        "Name": "Q",
        "MemberCount": 10,
        "MemberNames": [
          "CE:CC",
          "CE:PNS:Count",
          "CE:N",
          "SE:RA:Count",
          "SE:LT:Count",
          "SE:LT:0:Key",
          "SE:LT:0:Value",
          "Q:PA:Count",
          "Q:Q",
          "Q:A"
        ]
      },
      "MemberTypeInfo": {
        "BinaryTypeEnums": [
          "Object",
          "Primitive",
          "String",
          "Primitive",
          "Primitive",
          "String",
          "String",
          "Primitive",
          "Class",
          "Class"
        ],
        "AdditionalInfos": [
          null,
          "Int32",
          null,
          "Int32",
          "Int32",
          null,
          null,
          "Int32",
          {
            "TypeName": "A4",
            "LibraryId": 2
          },
          {
            "TypeName": "A4",
            "LibraryId": 2
          }
        ]
      },
      "LibraryId": 2,
      "Values": [
        {
          "RecordTypeEnum": "ObjectNull"
        },
        0,
        {
          "ObjectId": 46,
          "Value": "There is something special about the cla (ce983a60-8069-4120-8a81-1e83b73ae033)",
          "RecordTypeEnum": "BinaryObjectString"
        },
        0,
        1,
        {
          "IdRef": 8,
          "RecordTypeEnum": "MemberReference"
        },
        {
          "ObjectId": 48,
          "Value": "There is something special about the clanking of cutlery in this place. I've really grown fond of it.",
          "RecordTypeEnum": "BinaryObjectString"
        },
        0,
        {
          "IdRef": 9,
          "RecordTypeEnum": "MemberReference"
        },
        {
          "IdRef": 10,
          "RecordTypeEnum": "MemberReference"
        }
      ],
      "RecordTypeEnum": "ClassWithMembersAndTypes"
    },
    {
      "ClassInfo": {
        "ObjectId": 25,
        "Name": "Q",
        "MemberCount": 10,
        "MemberNames": [
          "CE:CC",
          "CE:PNS:Count",
          "CE:N",
          "SE:RA:Count",
          "SE:LT:Count",
          "SE:LT:0:Key",
          "SE:LT:0:Value",
          "Q:PA:Count",
          "Q:Q",
          "Q:A"
        ]
      },
      "MemberTypeInfo": {
        "BinaryTypeEnums": [
          "Object",
          "Primitive",
          "String",
          "Primitive",
          "Primitive",
          "String",
          "String",
          "Primitive",
          "Class",
          "Class"
        ],
        "AdditionalInfos": [
          null,
          "Int32",
          null,
          "Int32",
          "Int32",
          null,
          null,
          "Int32",
          {
            "TypeName": "A4",
            "LibraryId": 2
          },
          {
            "TypeName": "A4",
            "LibraryId": 2
          }
        ]
      },
      "LibraryId": 2,
      "Values": [
        {
          "RecordTypeEnum": "ObjectNull"
        },
        0,
        {
          "ObjectId": 51,
          "Value": "Doing fine, $(context.player.Name)? (8c0b69d2-5d31-41cc-bc45-63b26bdaeddb)",
          "RecordTypeEnum": "BinaryObjectString"
        },
        0,
        1,
        {
          "IdRef": 8,
          "RecordTypeEnum": "MemberReference"
        },
        {
          "ObjectId": 53,
          "Value": "Doing fine, $(context.player.Name)?",
          "RecordTypeEnum": "BinaryObjectString"
        },
        0,
        {
          "IdRef": 9,
          "RecordTypeEnum": "MemberReference"
        },
        {
          "IdRef": 10,
          "RecordTypeEnum": "MemberReference"
        }
      ],
      "RecordTypeEnum": "ClassWithMembersAndTypes"
    },
    {
      "ClassInfo": {
        "ObjectId": 26,
        "Name": "Q",
        "MemberCount": 10,
        "MemberNames": [
          "CE:CC",
          "CE:PNS:Count",
          "CE:N",
          "SE:RA:Count",
          "SE:LT:Count",
          "SE:LT:0:Key",
          "SE:LT:0:Value",
          "Q:PA:Count",
          "Q:Q",
          "Q:A"
        ]
      },
      "MemberTypeInfo": {
        "BinaryTypeEnums": [
          "Object",
          "Primitive",
          "String",
          "Primitive",
          "Primitive",
          "String",
          "String",
          "Primitive",
          "Class",
          "Class"
        ],
        "AdditionalInfos": [
          null,
          "Int32",
          null,
          "Int32",
          "Int32",
          null,
          null,
          "Int32",
          {
            "TypeName": "A4",
            "LibraryId": 2
          },
          {
            "TypeName": "A4",
            "LibraryId": 2
          }
        ]
      },
      "LibraryId": 2,
      "Values": [
        {
          "RecordTypeEnum": "ObjectNull"
        },
        0,
        {
          "ObjectId": 56,
          "Value": "Did you know that Monsignor Gustav was s (4afbb24a-6a48-46e8-9561-f057ba55c2c6)",
          "RecordTypeEnum": "BinaryObjectString"
        },
        0,
        1,
        {
          "IdRef": 8,
          "RecordTypeEnum": "MemberReference"
        },
        {
          "ObjectId": 58,
          "Value": "Did you know that Monsignor Gustav was sitting at that same table over there when he choked to death. Tragic...",
          "RecordTypeEnum": "BinaryObjectString"
        },
        0,
        {
          "IdRef": 9,
          "RecordTypeEnum": "MemberReference"
        },
        {
          "IdRef": 10,
          "RecordTypeEnum": "MemberReference"
        }
      ],
      "RecordTypeEnum": "ClassWithMembersAndTypes"
    },
    {
      "ClassInfo": {
        "ObjectId": 27,
        "Name": "Q",
        "MemberCount": 10,
        "MemberNames": [
          "CE:CC",
          "CE:PNS:Count",
          "CE:N",
          "SE:RA:Count",
          "SE:LT:Count",
          "SE:LT:0:Key",
          "SE:LT:0:Value",
          "Q:PA:Count",
          "Q:Q",
          "Q:A"
        ]
      },
      "MemberTypeInfo": {
        "BinaryTypeEnums": [
          "Object",
          "Primitive",
          "String",
          "Primitive",
          "Primitive",
          "String",
          "String",
          "Primitive",
          "Class",
          "Class"
        ],
        "AdditionalInfos": [
          null,
          "Int32",
          null,
          "Int32",
          "Int32",
          null,
          null,
          "Int32",
          {
            "TypeName": "A4",
            "LibraryId": 2
          },
          {
            "TypeName": "A4",
            "LibraryId": 2
          }
        ]
      },
      "LibraryId": 2,
      "Values": [
        {
          "RecordTypeEnum": "ObjectNull"
        },
        0,
        {
          "ObjectId": 61,
          "Value": "Tchort guide the chef! (36befd16-490a-4072-ac78-7f6799412b48)",
          "RecordTypeEnum": "BinaryObjectString"
        },
        0,
        1,
        {
          "IdRef": 8,
          "RecordTypeEnum": "MemberReference"
        },
        {
          "ObjectId": 63,
          "Value": "Tchort guide the chef!",
          "RecordTypeEnum": "BinaryObjectString"
        },
        0,
        {
          "IdRef": 9,
          "RecordTypeEnum": "MemberReference"
        },
        {
          "IdRef": 10,
          "RecordTypeEnum": "MemberReference"
        }
      ],
      "RecordTypeEnum": "ClassWithMembersAndTypes"
    },
    {
      "ClassInfo": {
        "ObjectId": 28,
        "Name": "Q",
        "MemberCount": 10,
        "MemberNames": [
          "CE:CC",
          "CE:PNS:Count",
          "CE:N",
          "SE:RA:Count",
          "SE:LT:Count",
          "SE:LT:0:Key",
          "SE:LT:0:Value",
          "Q:PA:Count",
          "Q:Q",
          "Q:A"
        ]
      },
      "MemberTypeInfo": {
        "BinaryTypeEnums": [
          "Object",
          "Primitive",
          "String",
          "Primitive",
          "Primitive",
          "String",
          "String",
          "Primitive",
          "Class",
          "Class"
        ],
        "AdditionalInfos": [
          null,
          "Int32",
          null,
          "Int32",
          "Int32",
          null,
          null,
          "Int32",
          {
            "TypeName": "A4",
            "LibraryId": 2
          },
          {
            "TypeName": "A4",
            "LibraryId": 2
          }
        ]
      },
      "LibraryId": 2,
      "Values": [
        {
          "RecordTypeEnum": "ObjectNull"
        },
        0,
        {
          "ObjectId": 66,
          "Value": "Ugh... I might have ate a bit too much.. (82529834-77da-47d8-9ccd-2f79a7e7d250)",
          "RecordTypeEnum": "BinaryObjectString"
        },
        0,
        1,
        {
          "IdRef": 8,
          "RecordTypeEnum": "MemberReference"
        },
        {
          "ObjectId": 68,
          "Value": "Ugh... I might have ate a bit too much...",
          "RecordTypeEnum": "BinaryObjectString"
        },
        0,
        {
          "IdRef": 9,
          "RecordTypeEnum": "MemberReference"
        },
        {
          "IdRef": 10,
          "RecordTypeEnum": "MemberReference"
        }
      ],
      "RecordTypeEnum": "ClassWithMembersAndTypes"
    },
    {
      "ClassInfo": {
        "ObjectId": 30,
        "Name": "FAPA",
        "MemberCount": 1,
        "MemberNames": [
          "BA:N"
        ]
      },
      "MemberTypeInfo": {
        "BinaryTypeEnums": [
          "String"
        ],
        "AdditionalInfos": [
          null
        ]
      },
      "LibraryId": 2,
      "Values": [
        {
          "ObjectId": 71,
          "Value": "02d837ee-aa72-44a1-a5c9-48ebf61b20d0",
          "RecordTypeEnum": "BinaryObjectString"
        }
      ],
      "RecordTypeEnum": "ClassWithMembersAndTypes"
    },
    {
      "RecordTypeEnum": "MessageEnd"
    }
  ],
  "Compressed": false
}